biot_savart/__init__.py
biot_savart/biot_savart.py
biot_savart/geometry.py
biot_savart/inputs.py
biot_savart/plotting.py
biot_savart/static/coil.svg
biot_savart/static/coil_field.svg
biot_savart/static/helmholtz.svg
biot_savart/static/helmholtz_field.svg
biot_savart-0.3.dist-info/METADATA
biot_savart-0.3.dist-info/WHEEL
biot_savart-0.3.dist-info/top_level.txt
biot_savart-0.3.dist-info/RECORD
