Metadata-Version: 2.1
Name: biot-savart
Version: 0.3
Summary: Magnetic Field Computation Library.
Home-page: https://github.com/vuthalab/biot-savart
Author: Mingde Yin
Author-email: mdsuper@hotmail.com
License: BSD-3-Clause
Platform: UNKNOWN
Classifier: Programming Language :: Python :: 3
Classifier: License :: OSI Approved :: MIT License
Classifier: Operating System :: OS Independent
Requires-Python: >=3.6
Requires-Dist: numpy
Requires-Dist: matplotlib
Requires-Dist: scipy
